README.rst
setup.py
djappsettings/__init__.py
djappsettings/settings.py
djappsettings.egg-info/PKG-INFO
djappsettings.egg-info/SOURCES.txt
djappsettings.egg-info/dependency_links.txt
djappsettings.egg-info/pbr.json
djappsettings.egg-info/top_level.txt
tests/__init__.py
tests/default.py
tests/test_djappsettings.py