Metadata-Version: 1.1
Name: djappsettings
Version: 0.4.0
Summary: Per-app default settings for Django
Home-page: http://github.com/adammck/djappsettings
Author: Adam Mckaig
Author-email: adam.mckaig@gmail.com
License: BSD
Platform: UNKNOWN
Classifier: Topic :: Internet :: WWW/HTTP :: Dynamic Content
Classifier: Intended Audience :: Developers
Classifier: License :: OSI Approved :: BSD License
Classifier: Programming Language :: Python
Classifier: Programming Language :: Python :: 2.7
Classifier: Programming Language :: Python :: 3
Classifier: Programming Language :: Python :: 3.3
Classifier: Programming Language :: Python :: 3.4
Classifier: Framework :: Django
Classifier: Development Status :: 5 - Production/Stable
Classifier: Operating System :: OS Independent
